repoze.catalog-0.9.0-py3.6-nspkg.pth
benchmark/__init__.py
benchmark/benchmark.py
benchmark/benchmarks.txt
benchmark/intersection.py
benchmark/sortbench.py
repoze/catalog/__init__.py
repoze/catalog/catalog.py
repoze/catalog/compat.py
repoze/catalog/document.py
repoze/catalog/interfaces.py
repoze/catalog/migration.py
repoze/catalog/query.py
repoze/catalog/indexes/__init__.py
repoze/catalog/indexes/common.py
repoze/catalog/indexes/facet.py
repoze/catalog/indexes/field.py
repoze/catalog/indexes/keyword.py
repoze/catalog/indexes/path.py
repoze/catalog/indexes/path2.py
repoze/catalog/indexes/text.py
repoze/catalog/indexes/tests/__init__.py
repoze/catalog/indexes/tests/test_common.py
repoze/catalog/indexes/tests/test_facet.py
repoze/catalog/indexes/tests/test_field.py
repoze/catalog/indexes/tests/test_keyword.py
repoze/catalog/indexes/tests/test_path.py
repoze/catalog/indexes/tests/test_path2.py
repoze/catalog/indexes/tests/test_text.py
repoze/catalog/tests/__init__.py
repoze/catalog/tests/test_catalog.py
repoze/catalog/tests/test_document.py
repoze/catalog/tests/test_functional.py
repoze/catalog/tests/test_migration.py
repoze/catalog/tests/test_query.py
repoze.catalog-0.9.0.dist-info/LICENSE.txt
repoze.catalog-0.9.0.dist-info/METADATA
repoze.catalog-0.9.0.dist-info/WHEEL
repoze.catalog-0.9.0.dist-info/namespace_packages.txt
repoze.catalog-0.9.0.dist-info/top_level.txt
repoze.catalog-0.9.0.dist-info/RECORD
