Metadata-Version: 2.1
Name: repoze.catalog
Version: 0.9.0
Summary: Searching and indexing based on zope.index
Home-page: http://www.repoze.org
Author: Agendaless Consulting
Author-email: repoze-dev@lists.repoze.org
License: BSD-derived (http://www.repoze.org/LICENSE.txt)
Keywords: indexing catalog search
Platform: UNKNOWN
Classifier: Intended Audience :: Developers
Classifier: Programming Language :: Python
Classifier: Programming Language :: Python :: 2
Classifier: Programming Language :: Python :: 2.7
Classifier: Programming Language :: Python :: 3
Classifier: Programming Language :: Python :: 3.6
Classifier: Programming Language :: Python :: 3.7
Classifier: Programming Language :: Python :: Implementation :: CPython
Classifier: Topic :: Internet :: WWW/HTTP :: Indexing/Search
Requires-Dist: setuptools
Requires-Dist: zope.component
Requires-Dist: ZODB3
Requires-Dist: zope.index (>=3.5.0)
Provides-Extra: benchmark
Requires-Dist: PyChart ; extra == 'benchmark'
Provides-Extra: docs
Requires-Dist: Sphinx ; extra == 'docs'
Provides-Extra: testing
Requires-Dist: nose ; extra == 'testing'
Requires-Dist: coverage ; extra == 'testing'
